l18n/__init__.py
l18n/__maps.py
l18n/compat.py
l18n/maps.py
l18n/translation.py
l18n/utils.py
l18n/version.py
l18n/locale/cs/LC_MESSAGES/l18n.mo
l18n/locale/de/LC_MESSAGES/l18n.mo
l18n/locale/en/LC_MESSAGES/l18n.mo
l18n/locale/fr/LC_MESSAGES/l18n.mo
l18n/locale/zh/LC_MESSAGES/l18n.mo
l18n-2021.3.dist-info/LICENSE.txt
l18n-2021.3.dist-info/METADATA
l18n-2021.3.dist-info/WHEEL
l18n-2021.3.dist-info/top_level.txt
l18n-2021.3.dist-info/RECORD
