Metadata-Version: 1.1
Name: l18n
Version: 2021.3
Summary: Internationalization for pytz timezones and territories
Home-page: https://github.com/tkhyn/l18n
Author: Thomas Khyn
Author-email: thomas@ksytek.com
License: UNKNOWN
Keywords: pytz,translation,i18n
Platform: UNKNOWN
Classifier: Programming Language :: Python
Classifier: Programming Language :: Python :: 3
Classifier: License :: OSI Approved :: MIT License
Classifier: Operating System :: OS Independent
Classifier: Development Status :: 5 - Production/Stable
Classifier: Intended Audience :: Developers
Classifier: Environment :: Other Environment
Classifier: Topic :: Software Development :: Internationalization
